{"peopleInfoResult": {"peopleInfo": {"peopleCd": "20308852", "peopleNm": "\uc804\uaddc\ub9ac", "peopleNmEn": "JEON Kyu-ri", "sex": "\uc5ec\uc790", "repRoleNm": "\uac10\ub3c5", "homepages": [], "filmos": [{"movieCd": "20206905", "movieNm": "\ub2e4\uc2e0, \ud0dc\uc5b4\ub098, \ub2e4\uc2dc", "moviePartNm": "\uac10\ub3c5"}, {"movieCd": "20206905", "movieNm": "\ub2e4\uc2e0, \ud0dc\uc5b4\ub098, \ub2e4\uc2dc", "moviePartNm": "\ubc30\uc6b0"}, {"movieCd": "20206905", "movieNm": "\ub2e4\uc2e0, \ud0dc\uc5b4\ub098, \ub2e4\uc2dc", "moviePartNm": "\ud3b8\uc9d1"}, {"movieCd": "20189063", "movieNm": "\uc2a4\uc717 \uace8\ub4e0 \ud0a4\uc704", "moviePartNm": "\uac10\ub3c5"}]}, "source": "\uc601\ud654\uc9c4\ud765\uc704\uc6d0\ud68c"}}