{"movieListResult": {"totCnt": 82557, "source": "\uc601\ud654\uc9c4\ud765\uc704\uc6d0\ud68c", "movieList": [{"movieCd": "20197922", "movieNm": "\ub2e4\ub9cc \uc545\uc5d0\uc11c \uad6c\ud558\uc18c\uc11c", "movieNmEn": "DELIVER US FROM EVIL", "prdtYear": "2019", "openDt": "20200805", "typeNm": "\uc7a5\ud3b8", "prdtStatNm": "\uac1c\ubd09", "nationAlt": "\ud55c\uad6d", "genreAlt": "\ubc94\uc8c4,\uc561\uc158", "repNationNm": "\ud55c\uad6d", "repGenreNm": "\ubc94\uc8c4", "directors": [{"peopleNm": "\ud64d\uc6d0\ucc2c"}], "companys": [{"companyCd": "2016841", "companyNm": "(\uc8fc)\ud558\uc774\ube0c\ubbf8\ub514\uc5b4\ucf54\ud504"}]}, {"movieCd": "20202711", "movieNm": "\uc81c3\ud68c \uc560\ub2c8\uba54\uc774\uc158 \uc5b4\uc6cc\uc988", "movieNmEn": "", "prdtYear": "2020", "openDt": "", "typeNm": "\uc634\ub2c8\ubc84\uc2a4", "prdtStatNm": "\uae30\ud0c0", "nationAlt": "\uae30\ud0c0", "genreAlt": "\uc560\ub2c8\uba54\uc774\uc158", "repNationNm": "\uae30\ud0c0", "repGenreNm": "\uc560\ub2c8\uba54\uc774\uc158", "directors": [], "companys": []}, {"movieCd": "20206647", "movieNm": "\uce68\ubb35 007\ube75", "movieNmEn": "Silent 007 Bang", "prdtYear": "2020", "openDt": "", "typeNm": "\ub2e8\ud3b8", "prdtStatNm": "\uae30\ud0c0", "nationAlt": "\ud55c\uad6d", "genreAlt": "\uc560\ub2c8\uba54\uc774\uc158", "repNationNm": "\ud55c\uad6d", "repGenreNm": "\uc560\ub2c8\uba54\uc774\uc158", "directors": [{"peopleNm": "\uc774\uc8fc\ud658"}], "companys": []}, {"movieCd": "20202705", "movieNm": "\uc790\ucde8\ud558\ub294 \uc606\uc9d1\ub204\ub098", "movieNmEn": "", "prdtYear": "2020", "openDt": "", "typeNm": "\uc7a5\ud3b8", "prdtStatNm": "\uae30\ud0c0", "nationAlt": "\uc77c\ubcf8", "genreAlt": "\ub4dc\ub77c\ub9c8", "repNationNm": "\uc77c\ubcf8", "repGenreNm": "\ub4dc\ub77c\ub9c8", "directors": [{"peopleNm": "\uc544\ub77c\uc2dc\uc57c\ub9c8 \ubbf8\uce58\ub8e8"}], "companys": []}, {"movieCd": "20202704", "movieNm": "\ub0a8\uc131\uc804\uc6a9 \uc5d0\uc2a4\ud14c\ud2f1", "movieNmEn": "", "prdtYear": "2020", "openDt": "", "typeNm": "\uc7a5\ud3b8", "prdtStatNm": "\uae30\ud0c0", "nationAlt": "\uc77c\ubcf8", "genreAlt": "\ub4dc\ub77c\ub9c8", "repNationNm": "\uc77c\ubcf8", "repGenreNm": "\ub4dc\ub77c\ub9c8", "directors": [{"peopleNm": "\ud56b\uc2dc\uc774"}], "companys": []}, {"movieCd": "20201123", "movieNm": "\ud504\ub9ac\ud0a4 \ub370\uc2a4\ub370\uc774", "movieNmEn": "Freaky", "prdtYear": "2020", "openDt": "20201125", "typeNm": "\uc7a5\ud3b8", "prdtStatNm": "\uac1c\ubd09", "nationAlt": "\ubbf8\uad6d", "genreAlt": "\ucf54\ubbf8\ub514,\uacf5\ud3ec(\ud638\ub7ec)", "repNationNm": "\ubbf8\uad6d", "repGenreNm": "\ucf54\ubbf8\ub514", "directors": [{"peopleNm": "\ud06c\ub9ac\uc2a4\ud1a0\ud37c \ub79c\ub358"}], "companys": []}, {"movieCd": "20200374", "movieNm": "\ucd5c\ubbf8\uc5ed\ud589", "movieNmEn": "The most beautiful retrograde", "prdtYear": "2020", "openDt": "20201125", "typeNm": "\uc7a5\ud3b8", "prdtStatNm": "\uac1c\ubd09", "nationAlt": "\uc911\uad6d", "genreAlt": "\ub4dc\ub77c\ub9c8", "repNationNm": "\uc911\uad6d", "repGenreNm": "\ub4dc\ub77c\ub9c8", "directors": [{"peopleNm": "\ud310\uc704\ub9b0"}], "companys": []}, {"movieCd": "20200475", "movieNm": "\ub85c\uadf8", "movieNmEn": "Rogue", "prdtYear": "2020", "openDt": "20201125", "typeNm": "\uc7a5\ud3b8", "prdtStatNm": "\uac1c\ubd09", "nationAlt": "\ubbf8\uad6d", "genreAlt": "\uc561\uc158", "repNationNm": "\ubbf8\uad6d", "repGenreNm": "\uc561\uc158", "directors": [{"peopleNm": "M.J. \ubc84\uc138\ud2b8"}], "companys": []}, {"movieCd": "20202513", "movieNm": "\ud56b \ubc14\ub514 \ub9ac\uc5bc\ub3cc:\ud669\ud640\ud55c \uc815\uc0ac", "movieNmEn": "", "prdtYear": "2019", "openDt": "20201124", "typeNm": "\uc7a5\ud3b8", "prdtStatNm": "\uac1c\ubd09", "nationAlt": "\uc77c\ubcf8", "genreAlt": "\uba5c\ub85c/\ub85c\ub9e8\uc2a4,\ub4dc\ub77c\ub9c8", "repNationNm": "\uc77c\ubcf8", "repGenreNm": "\uba5c\ub85c/\ub85c\ub9e8\uc2a4", "directors": [{"peopleNm": "\ucf54\uc774\ucf00.Jp"}], "companys": []}, {"movieCd": "20202511", "movieNm": "\uc816\uc5b4\ubc84\ub9b0 \uc544\ub0b4:\ub9cc\uc871\uc2dc\ucf1c \ub4dc\ub9b4\uac8c\uc694", "movieNmEn": "", "prdtYear": "2019", "openDt": "20201124", "typeNm": "\uc7a5\ud3b8", "prdtStatNm": "\uac1c\ubd09", "nationAlt": "\uc77c\ubcf8", "genreAlt": "\uba5c\ub85c/\ub85c\ub9e8\uc2a4,\ub4dc\ub77c\ub9c8", "repNationNm": "\uc77c\ubcf8", "repGenreNm": "\uba5c\ub85c/\ub85c\ub9e8\uc2a4", "directors": [{"peopleNm": "\uc0ac\ub178 B\uc0ac\ucfe0"}], "companys": []}, {"movieCd": "20202514", "movieNm": "\uc774\uc6c3\uc5ec\uc790:\ub2e4 \ubcf4\uc5ec\uc904\uac8c", "movieNmEn": "", "prdtYear": "2019", "openDt": "20201124", "typeNm": "\uc7a5\ud3b8", "prdtStatNm": "\uac1c\ubd09", "nationAlt": "\uc77c\ubcf8", "genreAlt": "\uba5c\ub85c/\ub85c\ub9e8\uc2a4,\ub4dc\ub77c\ub9c8", "repNationNm": "\uc77c\ubcf8", "repGenreNm": "\uba5c\ub85c/\ub85c\ub9e8\uc2a4", "directors": [{"peopleNm": "\uc2dc\uc628"}], "companys": []}, {"movieCd": "20202480", "movieNm": "\uc544\ub0b4 \ubab0\ub798 \uc7a5\ubaa8\ub2d8\uc774 \uc784\uc2e0\ud588\uc2b5\ub2c8\ub2e4", "movieNmEn": "", "prdtYear": "2019", "openDt": "", "typeNm": "\uc7a5\ud3b8", "prdtStatNm": "\uae30\ud0c0", "nationAlt": "\uc77c\ubcf8", "genreAlt": "\uc131\uc778\ubb3c(\uc5d0\ub85c),\ub4dc\ub77c\ub9c8", "repNationNm": "\uc77c\ubcf8", "repGenreNm": "\uc131\uc778\ubb3c(\uc5d0\ub85c)", "directors": [{"peopleNm": "\ub9c8\uba54\uc790\uc640 \ub9c8\uba54\ud0c0\ub85c"}], "companys": []}, {"movieCd": "20202479", "movieNm": "\uc0c1\uc0ac\ub97c \uc704\ud574 \uc816\uc5b4\ubc84\ub9b0 \uc721\uccb4 \ub178\ub9ac\uac1c", "movieNmEn": "", "prdtYear": "2019", "openDt": "", "typeNm": "\uc7a5\ud3b8", "prdtStatNm": "\uae30\ud0c0", "nationAlt": "\uc77c\ubcf8", "genreAlt": "\uc131\uc778\ubb3c(\uc5d0\ub85c),\ub4dc\ub77c\ub9c8", "repNationNm": "\uc77c\ubcf8", "repGenreNm": "\uc131\uc778\ubb3c(\uc5d0\ub85c)", "directors": [], "companys": []}, {"movieCd": "20202512", "movieNm": "\ubc1c\uc815\ub09c \uc544\ub0b4\uc758 \uc720\ud639", "movieNmEn": "", "prdtYear": "2019", "openDt": "20201124", "typeNm": "\uc7a5\ud3b8", "prdtStatNm": "\uac1c\ubd09", "nationAlt": "\uc77c\ubcf8", "genreAlt": "\uba5c\ub85c/\ub85c\ub9e8\uc2a4,\ub4dc\ub77c\ub9c8", "repNationNm": "\uc77c\ubcf8", "repGenreNm": "\uba5c\ub85c/\ub85c\ub9e8\uc2a4", "directors": [{"peopleNm": "\ud788\uc774\ub77c\uae30 \uc5d4\ubd80"}], "companys": []}, {"movieCd": "20202426", "movieNm": "\ub9c8\uc0ac\uc9c0\uc0ac\uc758 \uc695\ub9dd\uc744 \uc138\uc6cc\uc8fc\ub294 \uc548\ub0b4\uc6d0", "movieNmEn": "", "prdtYear": "2019", "openDt": "", "typeNm": "\uc7a5\ud3b8", "prdtStatNm": "\uae30\ud0c0", "nationAlt": "\uc77c\ubcf8", "genreAlt": "\uc131\uc778\ubb3c(\uc5d0\ub85c),\ub4dc\ub77c\ub9c8", "repNationNm": "\uc77c\ubcf8", "repGenreNm": "\uc131\uc778\ubb3c(\uc5d0\ub85c)", "directors": [], "companys": []}, {"movieCd": "20202248", "movieNm": "\ud658\uc601\ud569\ub2c8\ub2e4 \ube4c\ub77c \ubca8\ub77c", "movieNmEn": "Villa Bella", "prdtYear": "2019", "openDt": "", "typeNm": "\uc7a5\ud3b8", "prdtStatNm": "\uae30\ud0c0", "nationAlt": "\uc774\ud0c8\ub9ac\uc544", "genreAlt": "\ub4dc\ub77c\ub9c8", "repNationNm": "\uc774\ud0c8\ub9ac\uc544", "repGenreNm": "\ub4dc\ub77c\ub9c8", "directors": [], "companys": []}, {"movieCd": "20202688", "movieNm": "\ucf54\ub07c\ub9ac\uc640 \ub098\ube44", "movieNmEn": "The Elephant and the Butterfly", "prdtYear": "2017", "openDt": "", "typeNm": "\uc7a5\ud3b8", "prdtStatNm": "\uae30\ud0c0", "nationAlt": "\ubca8\uae30\uc5d0", "genreAlt": "\ub4dc\ub77c\ub9c8,\uac00\uc871", "repNationNm": "\ubca8\uae30\uc5d0", "repGenreNm": "\ub4dc\ub77c\ub9c8", "directors": [], "companys": []}, {"movieCd": "20198429", "movieNm": "\uc790\ubc31", "movieNmEn": "", "prdtYear": "2020", "openDt": "", "typeNm": "\uc7a5\ud3b8", "prdtStatNm": "\ud6c4\ubc18\uc791\uc5c5", "nationAlt": "\ud55c\uad6d", "genreAlt": "\ubc94\uc8c4,\uc2a4\ub9b4\ub7ec", "repNationNm": "\ud55c\uad6d", "repGenreNm": "\ubc94\uc8c4", "directors": [{"peopleNm": "\uc724\uc885\uc11d"}], "companys": [{"companyCd": "20100540", "companyNm": "\ub9ac\uc5bc\ub77c\uc774\uc988\ud53d\uccd0\uc2a4(\uc8fc)"}]}, {"movieCd": "20202665", "movieNm": "\ub9c8\uc74c\uc758 \uc18c\ub9ac \uc2a4\ud398\uc15c 4 - \uc2a4\ud399\ud0c0\ud074 \uc784\ud329\ud2b8\ub9e8", "movieNmEn": "", "prdtYear": "2020", "openDt": "", "typeNm": "\uc7a5\ud3b8", "prdtStatNm": "\uae30\ud0c0", "nationAlt": "\ud55c\uad6d", "genreAlt": "\uc560\ub2c8\uba54\uc774\uc158,\ucf54\ubbf8\ub514", "repNationNm": "\ud55c\uad6d", "repGenreNm": "\uc560\ub2c8\uba54\uc774\uc158", "directors": [], "companys": []}, {"movieCd": "20201004", "movieNm": "\ud5c8\ub9ac \uace0 \ub77c\uc6b4\ub4dc", "movieNmEn": "Hurry Go Round", "prdtYear": "2018", "openDt": "", "typeNm": "\uc7a5\ud3b8", "prdtStatNm": "\uae30\ud0c0", "nationAlt": "\uc77c\ubcf8", "genreAlt": "\ub2e4\ud050\uba58\ud130\ub9ac", "repNationNm": "\uc77c\ubcf8", "repGenreNm": "\ub2e4\ud050\uba58\ud130\ub9ac", "directors": [], "companys": []}, {"movieCd": "20196264", "movieNm": "\uc720\uccb4\uc774\ud0c8\uc790", "movieNmEn": "Spiritwalker", "prdtYear": "2020", "openDt": "", "typeNm": "\uc7a5\ud3b8", "prdtStatNm": "\ud6c4\ubc18\uc791\uc5c5", "nationAlt": "\ud55c\uad6d", "genreAlt": "\ud310\ud0c0\uc9c0,\uc561\uc158", "repNationNm": "\ud55c\uad6d", "repGenreNm": "\ud310\ud0c0\uc9c0", "directors": [{"peopleNm": "\uc724\uc7ac\uadfc"}], "companys": [{"companyCd": "20138935", "companyNm": "(\uc8fc)\ube44\uc5d0\uc774\uc5d4\ud130\ud14c\uc778\uba3c\ud2b8"}, {"companyCd": "20122494", "companyNm": "(\uc8fc)\uc0ac\ub78c\uc5d4\ud130\ud14c\uc778\uba3c\ud2b8"}]}, {"movieCd": "20206683", "movieNm": "\uc2a4\uc640\ud2b8: \ud0c0\uc784 \ud06c\ub77c\uc774\uc2dc\uc2a4", "movieNmEn": "SWAT DUTY: CITY CRISIS", "prdtYear": "2020", "openDt": "", "typeNm": "\uc7a5\ud3b8", "prdtStatNm": "\uae30\ud0c0", "nationAlt": "\uc911\uad6d", "genreAlt": "\uc561\uc158,\ubc94\uc8c4", "repNationNm": "\uc911\uad6d", "repGenreNm": "\uc561\uc158", "directors": [], "companys": []}, {"movieCd": "20202070", "movieNm": "\ubc30\ub4dc \uc9c0\ub2c8\uc5b4\uc2a4 \ub354 \uc2dc\ub9ac\uc988: \ub77c\uc2a4\ud2b8 \uc139\uc158", "movieNmEn": "Bad Genius The Series: last section", "prdtYear": "2020", "openDt": "", "typeNm": "\uc7a5\ud3b8", "prdtStatNm": "\uae30\ud0c0", "nationAlt": "\uae30\ud0c0", "genreAlt": "\ubc94\uc8c4,\uc2a4\ub9b4\ub7ec,\ub4dc\ub77c\ub9c8", "repNationNm": "\uae30\ud0c0", "repGenreNm": "\ubc94\uc8c4", "directors": [], "companys": []}, {"movieCd": "20202069", "movieNm": "\ubc30\ub4dc \uc9c0\ub2c8\uc5b4\uc2a4 \ub354 \uc2dc\ub9ac\uc988: \uc139\uc158 5", "movieNmEn": "Bad Genius The Series: section 5", "prdtYear": "2020", "openDt": "", "typeNm": "\uc7a5\ud3b8", "prdtStatNm": "\uae30\ud0c0", "nationAlt": "\uae30\ud0c0", "genreAlt": "\ubc94\uc8c4,\uc2a4\ub9b4\ub7ec,\ub4dc\ub77c\ub9c8", "repNationNm": "\uae30\ud0c0", "repGenreNm": "\ubc94\uc8c4", "directors": [], "companys": []}, {"movieCd": "20182224", "movieNm": "\ud30c\uc2ac\ub9ac \uc18c\ub140", "movieNmEn": "Parsley Girl", "prdtYear": "2018", "openDt": "", "typeNm": "\ub2e8\ud3b8", "prdtStatNm": "\uae30\ud0c0", "nationAlt": "\ud55c\uad6d", "genreAlt": "\uc560\ub2c8\uba54\uc774\uc158", "repNationNm": "\ud55c\uad6d", "repGenreNm": "\uc560\ub2c8\uba54\uc774\uc158", "directors": [{"peopleNm": "\ub178\uc601\ubbf8"}], "companys": []}, {"movieCd": "20202648", "movieNm": "\ucd09\uc0b0\uc8042", "movieNmEn": "Shushan Subdues Evil", "prdtYear": "2019", "openDt": "", "typeNm": "\uc7a5\ud3b8", "prdtStatNm": "\uae30\ud0c0", "nationAlt": "\uc911\uad6d", "genreAlt": "\uc561\uc158", "repNationNm": "\uc911\uad6d", "repGenreNm": "\uc561\uc158", "directors": [], "companys": []}, {"movieCd": "20202392", "movieNm": "\ud37c\ud399\ud2b8 \uc774\uc2a4\ucf00\uc774\ud504", "movieNmEn": "The Discarded", "prdtYear": "2019", "openDt": "", "typeNm": "\uc7a5\ud3b8", "prdtStatNm": "\uae30\ud0c0", "nationAlt": "\uc601\uad6d", "genreAlt": "\uc2a4\ub9b4\ub7ec,\ub4dc\ub77c\ub9c8", "repNationNm": "\uc601\uad6d", "repGenreNm": "\uc2a4\ub9b4\ub7ec", "directors": [], "companys": []}, {"movieCd": "20201972", "movieNm": "\ub0b4\ub85c\ub0a8\ubd88", "movieNmEn": "", "prdtYear": "2020", "openDt": "20201123", "typeNm": "\uc7a5\ud3b8", "prdtStatNm": "\uac1c\ubd09", "nationAlt": "\ud55c\uad6d", "genreAlt": "\uba5c\ub85c/\ub85c\ub9e8\uc2a4,\ub4dc\ub77c\ub9c8", "repNationNm": "\ud55c\uad6d", "repGenreNm": "\uba5c\ub85c/\ub85c\ub9e8\uc2a4", "directors": [{"peopleNm": "\uc724\uc900\uc138"}], "companys": [{"companyCd": "20114899", "companyNm": "(\uc8fc)\uc601\uc9c4\ud06c\ub9ac\uc5d0\uc774\ud2f0\ube0c"}]}, {"movieCd": "20202590", "movieNm": "\ub3c4\ub828\ub2d8\uacfc \ubc14\ub78c\ub09c \uc544\ub0b4", "movieNmEn": "Bonds and love", "prdtYear": "2020", "openDt": "", "typeNm": "\uc7a5\ud3b8", "prdtStatNm": "\uae30\ud0c0", "nationAlt": "\uc77c\ubcf8", "genreAlt": "\ub4dc\ub77c\ub9c8,\uc131\uc778\ubb3c(\uc5d0\ub85c)", "repNationNm": "\uc77c\ubcf8", "repGenreNm": "\ub4dc\ub77c\ub9c8", "directors": [{"peopleNm": "\uc0ac\ud0a4\ud0c0\ub9c8 \uc870\uc9c0"}], "companys": []}, {"movieCd": "20202589", "movieNm": "\ub2f9\uc2e0\uc758 \uc544\ub0b4\uac00 \uc57c\uadfc\ud55c\ub2e4\uba74", "movieNmEn": "Revenge of misunderstanding", "prdtYear": "2020", "openDt": "", "typeNm": "\uc7a5\ud3b8", "prdtStatNm": "\uae30\ud0c0", "nationAlt": "\uc77c\ubcf8", "genreAlt": "\ub4dc\ub77c\ub9c8,\uc131\uc778\ubb3c(\uc5d0\ub85c)", "repNationNm": "\uc77c\ubcf8", "repGenreNm": "\ub4dc\ub77c\ub9c8", "directors": [{"peopleNm": "\uc7a0\ud30c"}], "companys": []}, {"movieCd": "20202623", "movieNm": "\uc5b4\ub9b0\ucc98\uc81c \uadf8\ub9ac\uace0.. \uce5c\uad6c", "movieNmEn": "", "prdtYear": "2020", "openDt": "", "typeNm": "\uc7a5\ud3b8", "prdtStatNm": "\uae30\ud0c0", "nationAlt": "\ud55c\uad6d", "genreAlt": "\uba5c\ub85c/\ub85c\ub9e8\uc2a4", "repNationNm": "\ud55c\uad6d", "repGenreNm": "\uba5c\ub85c/\ub85c\ub9e8\uc2a4", "directors": [], "companys": [{"companyCd": "20102239", "companyNm": "\ub808\ub4dc \uce74\ud3ab \ud504\ub85c\ub355\uc158"}]}, {"movieCd": "20202586", "movieNm": "\uc5d0\ubc00\ub9ac\uc544\uc758 \ub178\ub3d9\uc790\ub4e4\uc740 \uc4f0\ub7ec\uc9c0\uc9c0 \uc54a\ub294\ub2e4", "movieNmEn": "Don\u2019t be afraid of the night", "prdtYear": "2016", "openDt": "", "typeNm": "\uc7a5\ud3b8", "prdtStatNm": "\uae30\ud0c0", "nationAlt": "\uc774\ud0c8\ub9ac\uc544", "genreAlt": "\ub4dc\ub77c\ub9c8", "repNationNm": "\uc774\ud0c8\ub9ac\uc544", "repGenreNm": "\ub4dc\ub77c\ub9c8", "directors": [], "companys": []}, {"movieCd": "20206815", "movieNm": "\uc5ec\ub3d9\uc0dd\uacfc \uc740\ubc00\ud55c \uac70\ub798", "movieNmEn": "", "prdtYear": "2020", "openDt": "20201112", "typeNm": "\uc7a5\ud3b8", "prdtStatNm": "\uac1c\ubd09", "nationAlt": "\ud55c\uad6d", "genreAlt": "\uba5c\ub85c/\ub85c\ub9e8\uc2a4,\uc131\uc778\ubb3c(\uc5d0\ub85c)", "repNationNm": "\ud55c\uad6d", "repGenreNm": "\uba5c\ub85c/\ub85c\ub9e8\uc2a4", "directors": [{"peopleNm": "\uc724\uacbd\uc2dd"}], "companys": [{"companyCd": "20157008", "companyNm": "(\uc8fc)\ud53d\uccd0\ub808\uc2a4\ud06c"}]}, {"movieCd": "20209351", "movieNm": "\ub098\uc774\uc2a4 \uac78 \ub77c\uc774\ud06c \uc720", "movieNmEn": "A Nice Girl Like You", "prdtYear": "2020", "openDt": "20201118", "typeNm": "\uc7a5\ud3b8", "prdtStatNm": "\uac1c\ubd09", "nationAlt": "\ubbf8\uad6d", "genreAlt": "\ucf54\ubbf8\ub514,\uba5c\ub85c/\ub85c\ub9e8\uc2a4", "repNationNm": "\ubbf8\uad6d", "repGenreNm": "\ucf54\ubbf8\ub514", "directors": [], "companys": []}, {"movieCd": "20202369", "movieNm": "\uadf8 \ud45c\uc815", "movieNmEn": "ego", "prdtYear": "2020", "openDt": "", "typeNm": "\ub2e8\ud3b8", "prdtStatNm": "\uae30\ud0c0", "nationAlt": "\ud55c\uad6d", "genreAlt": "\ud310\ud0c0\uc9c0", "repNationNm": "\ud55c\uad6d", "repGenreNm": "\ud310\ud0c0\uc9c0", "directors": [{"peopleNm": "\uc870\ud55c\uae30"}], "companys": []}, {"movieCd": "20207495", "movieNm": "\ud2b9\uc218\uc694\uc6d0", "movieNmEn": "", "prdtYear": "2020", "openDt": "", "typeNm": "\uc7a5\ud3b8", "prdtStatNm": "\uae30\ud0c0", "nationAlt": "\ud55c\uad6d", "genreAlt": "\uc561\uc158", "repNationNm": "\ud55c\uad6d", "repGenreNm": "\uc561\uc158", "directors": [{"peopleNm": "\uc2e0\uc7ac\uba85"}], "companys": [{"companyCd": "20154628", "companyNm": "(\uc8fc)\uc601\ud654\uc0ac \uc0ac\uacc4\uc808"}]}, {"movieCd": "20202562", "movieNm": "[\uc791\uc740\uc601\ud654\uc601\ud654\uc81c] \uc2dc\ub9b0 \uc138\uc0c1,\uc5bc\uc5b4\ubd99\uc9c0 \uc54a\ub294 \ub9c8\uc74c\ub4e4", "movieNmEn": "", "prdtYear": "2020", "openDt": "", "typeNm": "\uc634\ub2c8\ubc84\uc2a4", "prdtStatNm": "\uae30\ud0c0", "nationAlt": "\ud55c\uad6d", "genreAlt": "\uae30\ud0c0", "repNationNm": "\ud55c\uad6d", "repGenreNm": "\uae30\ud0c0", "directors": [], "companys": []}, {"movieCd": "20202538", "movieNm": "\uc2a4\ub098\uc774\ud37c", "movieNmEn": "", "prdtYear": "2020", "openDt": "", "typeNm": "\uae30\ud0c0", "prdtStatNm": "\uae30\ud0c0", "nationAlt": "\uc911\uad6d", "genreAlt": "\uae30\ud0c0", "repNationNm": "\uc911\uad6d", "repGenreNm": "\uae30\ud0c0", "directors": [], "companys": []}, {"movieCd": "20202552", "movieNm": "\ud2b9\uacf5\ud669\ube44", "movieNmEn": "Princess the Secret Service Part 1", "prdtYear": "2018", "openDt": "", "typeNm": "\uc7a5\ud3b8", "prdtStatNm": "\uae30\ud0c0", "nationAlt": "\uc911\uad6d", "genreAlt": "\uc561\uc158", "repNationNm": "\uc911\uad6d", "repGenreNm": "\uc561\uc158", "directors": [], "companys": []}, {"movieCd": "20202517", "movieNm": "\uac70\uc720 \uac04\ud638 \ud074\ub9ac\ub2c9 2", "movieNmEn": "Love and hate -reunion-", "prdtYear": "2020", "openDt": "", "typeNm": "\uc7a5\ud3b8", "prdtStatNm": "\uae30\ud0c0", "nationAlt": "\uc77c\ubcf8", "genreAlt": "\ub4dc\ub77c\ub9c8,\uc131\uc778\ubb3c(\uc5d0\ub85c)", "repNationNm": "\uc77c\ubcf8", "repGenreNm": "\ub4dc\ub77c\ub9c8", "directors": [{"peopleNm": "\uc624\uc790\ud0a4 \ud788\ub85c\ucf54\uc6b0\uc9c0"}], "companys": []}, {"movieCd": "20202516", "movieNm": "\uac70\uc720 \uac04\ud638 \ud074\ub9ac\ub2c9", "movieNmEn": "Love and hate \u2013jealousy-", "prdtYear": "2020", "openDt": "", "typeNm": "\uc7a5\ud3b8", "prdtStatNm": "\uae30\ud0c0", "nationAlt": "\uc77c\ubcf8", "genreAlt": "\ub4dc\ub77c\ub9c8,\uc131\uc778\ubb3c(\uc5d0\ub85c)", "repNationNm": "\uc77c\ubcf8", "repGenreNm": "\ub4dc\ub77c\ub9c8", "directors": [{"peopleNm": "\uc7a0\ud30c"}], "companys": []}, {"movieCd": "20198870", "movieNm": "\uc5b4\uac8c\uc778", "movieNmEn": "Again", "prdtYear": "2018", "openDt": "20200730", "typeNm": "\uc7a5\ud3b8", "prdtStatNm": "\uac1c\ubd09", "nationAlt": "\ud55c\uad6d", "genreAlt": "\ubba4\uc9c0\uceec,\ub4dc\ub77c\ub9c8", "repNationNm": "\ud55c\uad6d", "repGenreNm": "\ubba4\uc9c0\uceec", "directors": [{"peopleNm": "\uc870\ucc3d\uc5f4"}], "companys": [{"companyCd": "20188321", "companyNm": "(\uc8fc)\ud558\ub2ac\ubc14\ub78c"}]}, {"movieCd": "20040734", "movieNm": "\ub178\ud2b8\ubd81", "movieNmEn": "The Notebook", "prdtYear": "2004", "openDt": "20041126", "typeNm": "\uc7a5\ud3b8", "prdtStatNm": "\uac1c\ubd09", "nationAlt": "\ubbf8\uad6d", "genreAlt": "\uba5c\ub85c/\ub85c\ub9e8\uc2a4", "repNationNm": "\ubbf8\uad6d", "repGenreNm": "\uba5c\ub85c/\ub85c\ub9e8\uc2a4", "directors": [{"peopleNm": "\ub2c9 \uce74\uc0ac\ubca0\uce20"}], "companys": [{"companyCd": "20104412", "companyNm": "\ub274\ub77c\uc778 \uc2dc\ub124\ub9c8"}]}, {"movieCd": "19950185", "movieNm": "\ub2f9\uc2e0\uc774 \uc7a0\ub4e0 \uc0ac\uc774\uc5d0 ", "movieNmEn": "While You Were Sleeping", "prdtYear": "1994", "openDt": "19950513", "typeNm": "\uc7a5\ud3b8", "prdtStatNm": "\uac1c\ubd09", "nationAlt": "\ubbf8\uad6d", "genreAlt": "\ucf54\ubbf8\ub514", "repNationNm": "\ubbf8\uad6d", "repGenreNm": "\ucf54\ubbf8\ub514", "directors": [{"peopleNm": "\uc874 \ud130\ud2c0\ud0c0\uc6c1"}], "companys": [{"companyCd": "20102457", "companyNm": "\uce74\ub77c\ubc18 \ud53d\uccd0\uc2a4"}, {"companyCd": "20104107", "companyNm": "\ud560\ub9ac\uc6b0\ub4dc\ud53d\ucc98\uc2a4"}]}, {"movieCd": "20111367", "movieNm": "\uc0ac\uc774\ubc84 \uc790\uc0b4\ub2f9", "movieNmEn": "Suicide Room", "prdtYear": "2011", "openDt": "", "typeNm": "\uc7a5\ud3b8", "prdtStatNm": "\uae30\ud0c0", "nationAlt": "\ud3f4\ub780\ub4dc", "genreAlt": "\ub4dc\ub77c\ub9c8", "repNationNm": "\ud3f4\ub780\ub4dc", "repGenreNm": "\ub4dc\ub77c\ub9c8", "directors": [{"peopleNm": "\uc580 \ucf54\ub9c8\uc0ac"}], "companys": []}, {"movieCd": "20193666", "movieNm": "\uc624! \ubb38\ud76c", "movieNmEn": "Oh! My Gran", "prdtYear": "2020", "openDt": "20200902", "typeNm": "\uc7a5\ud3b8", "prdtStatNm": "\uac1c\ubd09", "nationAlt": "\ud55c\uad6d", "genreAlt": "\ucf54\ubbf8\ub514,\ub4dc\ub77c\ub9c8", "repNationNm": "\ud55c\uad6d", "repGenreNm": "\ucf54\ubbf8\ub514", "directors": [{"peopleNm": "\uc815\uc138\uad50"}], "companys": [{"companyCd": "20123063", "companyNm": "(\uc8fc)\ube45\uc2a4\ud1a4\ud53d\uccd0\uc2a4"}]}, {"movieCd": "20202510", "movieNm": "\uc5b4\ub9b0 \uc591", "movieNmEn": "The Other Lamb", "prdtYear": "2019", "openDt": "", "typeNm": "\uc7a5\ud3b8", "prdtStatNm": "\uae30\ud0c0", "nationAlt": "\uc544\uc77c\ub79c\ub4dc,\ubca8\uae30\uc5d0,\ubbf8\uad6d", "genreAlt": "\uae30\ud0c0", "repNationNm": "\uc544\uc77c\ub79c\ub4dc", "repGenreNm": "\uae30\ud0c0", "directors": [{"peopleNm": "\ub9c8\uc6b0\uace0\uc790\ud0c0 \uc288\ubaa8\ud504\uc2a4\uce74"}], "companys": []}, {"movieCd": "20202530", "movieNm": "\ub0af\uc120 \uc5ec\ud589", "movieNmEn": "Fugue", "prdtYear": "2018", "openDt": "", "typeNm": "\uc7a5\ud3b8", "prdtStatNm": "\uae30\ud0c0", "nationAlt": "\ud3f4\ub780\ub4dc,\uccb4\ucf54,\uc2a4\uc6e8\ub374", "genreAlt": "\uae30\ud0c0", "repNationNm": "\ud3f4\ub780\ub4dc", "repGenreNm": "\uae30\ud0c0", "directors": [], "companys": []}, {"movieCd": "20202509", "movieNm": "\uc5bc\ud504\ub9b0\uc2a4", "movieNmEn": "The Erlprince", "prdtYear": "2016", "openDt": "", "typeNm": "\uc7a5\ud3b8", "prdtStatNm": "\uae30\ud0c0", "nationAlt": "\ud3f4\ub780\ub4dc", "genreAlt": "\uae30\ud0c0", "repNationNm": "\ud3f4\ub780\ub4dc", "repGenreNm": "\uae30\ud0c0", "directors": [], "companys": []}, {"movieCd": "20200446", "movieNm": "\ub465\uc9c0", "movieNmEn": "Doong-ji", "prdtYear": "2020", "openDt": "", "typeNm": "\ub2e8\ud3b8", "prdtStatNm": "\uae30\ud0c0", "nationAlt": "\ud55c\uad6d", "genreAlt": "\ub4dc\ub77c\ub9c8,\uae30\ud0c0", "repNationNm": "\ud55c\uad6d", "repGenreNm": "\ub4dc\ub77c\ub9c8", "directors": [{"peopleNm": "\uc870\uacbd\uc6d0"}], "companys": []}, {"movieCd": "20202508", "movieNm": "\ub465\uc9c0", "movieNmEn": "Nest", "prdtYear": "2020", "openDt": "", "typeNm": "\ub2e8\ud3b8", "prdtStatNm": "\uae30\ud0c0", "nationAlt": "\ud55c\uad6d", "genreAlt": "\uae30\ud0c0", "repNationNm": "\ud55c\uad6d", "repGenreNm": "\uae30\ud0c0", "directors": [{"peopleNm": "\uae40\uacbd\ubb35"}], "companys": []}, {"movieCd": "20202529", "movieNm": "\ubaa8\ub798\uc2dc\uacc4 \uc694\uc591\uc6d0", "movieNmEn": "The Hour-Glass Sanatorium", "prdtYear": "1973", "openDt": "", "typeNm": "\uc7a5\ud3b8", "prdtStatNm": "\uae30\ud0c0", "nationAlt": "\ud3f4\ub780\ub4dc", "genreAlt": "\uae30\ud0c0", "repNationNm": "\ud3f4\ub780\ub4dc", "repGenreNm": "\uae30\ud0c0", "directors": [], "companys": []}, {"movieCd": "19738208", "movieNm": "\uacc4\ubabd", "movieNmEn": "The Illumination", "prdtYear": "1972", "openDt": "", "typeNm": "\uc7a5\ud3b8", "prdtStatNm": "\uae30\ud0c0", "nationAlt": "\ud3f4\ub780\ub4dc", "genreAlt": "\ub4dc\ub77c\ub9c8", "repNationNm": "\ud3f4\ub780\ub4dc", "repGenreNm": "\ub4dc\ub77c\ub9c8", "directors": [{"peopleNm": "\ud06c\uc9c0\uc26c\ud1a0\ud504 \uc790\ub204\uc26c"}], "companys": []}, {"movieCd": "20202507", "movieNm": "\uc545\ub9c8", "movieNmEn": "The Devil", "prdtYear": "1972", "openDt": "", "typeNm": "\uc7a5\ud3b8", "prdtStatNm": "\uae30\ud0c0", "nationAlt": "\ud3f4\ub780\ub4dc", "genreAlt": "\uae30\ud0c0", "repNationNm": "\ud3f4\ub780\ub4dc", "repGenreNm": "\uae30\ud0c0", "directors": [{"peopleNm": "\uc548\ub4dc\ub808\uc774 \uc904\ub78d\uc2a4\ud0a4"}], "companys": []}, {"movieCd": "20202528", "movieNm": "\uc7a5\ubcbd", "movieNmEn": "Barrier", "prdtYear": "1966", "openDt": "", "typeNm": "\uc7a5\ud3b8", "prdtStatNm": "\uae30\ud0c0", "nationAlt": "\ud3f4\ub780\ub4dc", "genreAlt": "\uae30\ud0c0", "repNationNm": "\ud3f4\ub780\ub4dc", "repGenreNm": "\uae30\ud0c0", "directors": [{"peopleNm": "\uc800\uc9c0 \uc2a4\ucf5c\ub9ac\ubaa8\uc6b0\uc2a4\ud0a4"}], "companys": []}, {"movieCd": "19998722", "movieNm": "\uae61\uc21c\uc774, \uc288\uc5b4 \ud504\ub85c\ub355\uce20 \ub178\ub3d9\uc790", "movieNmEn": "Kkangsuni", "prdtYear": "1989", "openDt": "", "typeNm": "\ub2e8\ud3b8", "prdtStatNm": "\uae30\ud0c0", "nationAlt": "\ud55c\uad6d", "genreAlt": "\ub2e4\ud050\uba58\ud130\ub9ac", "repNationNm": "\ud55c\uad6d", "repGenreNm": "\ub2e4\ud050\uba58\ud130\ub9ac", "directors": [{"peopleNm": "\uc774\uc0c1\uc778"}], "companys": []}, {"movieCd": "20202506", "movieNm": "\uacf5\uc911\uc81c\ube44", "movieNmEn": "Somersault", "prdtYear": "1965", "openDt": "", "typeNm": "\uc7a5\ud3b8", "prdtStatNm": "\uae30\ud0c0", "nationAlt": "\ud3f4\ub780\ub4dc", "genreAlt": "\uae30\ud0c0", "repNationNm": "\ud3f4\ub780\ub4dc", "repGenreNm": "\uae30\ud0c0", "directors": [], "companys": []}, {"movieCd": "20202505", "movieNm": "\uc21c\uc9c4\ud55c \ub9c8\ubc95\uc0ac", "movieNmEn": "Innocent Sorcerers", "prdtYear": "1960", "openDt": "", "typeNm": "\uc7a5\ud3b8", "prdtStatNm": "\uae30\ud0c0", "nationAlt": "\ud3f4\ub780\ub4dc", "genreAlt": "\uae30\ud0c0", "repNationNm": "\ud3f4\ub780\ub4dc", "repGenreNm": "\uae30\ud0c0", "directors": [{"peopleNm": "\uc548\uc81c\uc774 \ubc14\uc774\ub2e4"}], "companys": []}, {"movieCd": "20202504", "movieNm": "\uc120\ub85c \uc704\uc758 \uc0ac\ub78c", "movieNmEn": "Man on the Tracks", "prdtYear": "1957", "openDt": "", "typeNm": "\uc7a5\ud3b8", "prdtStatNm": "\uae30\ud0c0", "nationAlt": "\ud3f4\ub780\ub4dc", "genreAlt": "\uae30\ud0c0", "repNationNm": "\ud3f4\ub780\ub4dc", "repGenreNm": "\uae30\ud0c0", "directors": [], "companys": []}, {"movieCd": "20202527", "movieNm": "\uba39\uace0 \uc2f6\uc740 \uadf8\ub140", "movieNmEn": "", "prdtYear": "2020", "openDt": "", "typeNm": "\uc7a5\ud3b8", "prdtStatNm": "\uae30\ud0c0", "nationAlt": "\ud55c\uad6d", "genreAlt": "\uba5c\ub85c/\ub85c\ub9e8\uc2a4", "repNationNm": "\ud55c\uad6d", "repGenreNm": "\uba5c\ub85c/\ub85c\ub9e8\uc2a4", "directors": [{"peopleNm": "\ucd5c\uc9c4\ucca0"}], "companys": [{"companyCd": "20204981", "companyNm": "\ub77c\uc784\ud544\ub984"}]}, {"movieCd": "20209147", "movieNm": "\ubc14\ub78c\ub09c \uc544\ub0b4\uc758 \ube44\ubc00", "movieNmEn": "", "prdtYear": "2020", "openDt": "20201119", "typeNm": "\uc7a5\ud3b8", "prdtStatNm": "\uac1c\ubd09", "nationAlt": "\ud55c\uad6d", "genreAlt": "\uc131\uc778\ubb3c(\uc5d0\ub85c)", "repNationNm": "\ud55c\uad6d", "repGenreNm": "\uc131\uc778\ubb3c(\uc5d0\ub85c)", "directors": [{"peopleNm": "\uc724\uacbd\uc2dd"}], "companys": [{"companyCd": "20157008", "companyNm": "(\uc8fc)\ud53d\uccd0\ub808\uc2a4\ud06c"}]}, {"movieCd": "20207345", "movieNm": "\ub0b4 \uc544\ub0b4\uac00 \uc544\ub2cc", "movieNmEn": "", "prdtYear": "2020", "openDt": "20201119", "typeNm": "\uc7a5\ud3b8", "prdtStatNm": "\uac1c\ubd09", "nationAlt": "\ud55c\uad6d", "genreAlt": "\uc131\uc778\ubb3c(\uc5d0\ub85c)", "repNationNm": "\ud55c\uad6d", "repGenreNm": "\uc131\uc778\ubb3c(\uc5d0\ub85c)", "directors": [{"peopleNm": "\uc724\uacbd\uc2dd"}], "companys": [{"companyCd": "20157008", "companyNm": "(\uc8fc)\ud53d\uccd0\ub808\uc2a4\ud06c"}]}, {"movieCd": "20202503", "movieNm": "\ud558\ub4dc \ud398\uc778\ud2b8", "movieNmEn": "Hard Paint", "prdtYear": "2019", "openDt": "", "typeNm": "\uc7a5\ud3b8", "prdtStatNm": "\uae30\ud0c0", "nationAlt": "\ube0c\ub77c\uc9c8,\ub124\ub35c\ub780\ub4dc", "genreAlt": "\ub4dc\ub77c\ub9c8", "repNationNm": "\ube0c\ub77c\uc9c8", "repGenreNm": "\ub4dc\ub77c\ub9c8", "directors": [], "companys": []}, {"movieCd": "20202433", "movieNm": "\uad34\uc9dc\ub4e4\uc758 \ub85c\ub9e8\uc2a4", "movieNmEn": "", "prdtYear": "2020", "openDt": "", "typeNm": "\uc7a5\ud3b8", "prdtStatNm": "\uae30\ud0c0", "nationAlt": "\uae30\ud0c0", "genreAlt": "\uae30\ud0c0", "repNationNm": "\uae30\ud0c0", "repGenreNm": "\uae30\ud0c0", "directors": [], "companys": []}, {"movieCd": "20202431", "movieNm": "\uc778\ub514\ud3ec\ub7fc \uc6d4\ub840\ube44\ud589 11\uc6d4 \uc5fc\uc9c0\ud61c \uc791\uac00\uc804: \uafc8 \uc18d\uc758 \uafc8\uc5d0\uc11c \uae7c\uc744 \ub54c", "movieNmEn": "", "prdtYear": "2020", "openDt": "", "typeNm": "\uae30\ud0c0", "prdtStatNm": "\uae30\ud0c0", "nationAlt": "\ud55c\uad6d", "genreAlt": "\uae30\ud0c0", "repNationNm": "\ud55c\uad6d", "repGenreNm": "\uae30\ud0c0", "directors": [], "companys": []}, {"movieCd": "20202491", "movieNm": "\ub370\uc774\ud2b8", "movieNmEn": "", "prdtYear": "2016", "openDt": "", "typeNm": "\ub2e8\ud3b8", "prdtStatNm": "\uae30\ud0c0", "nationAlt": "\ud55c\uad6d", "genreAlt": "\uae30\ud0c0", "repNationNm": "\ud55c\uad6d", "repGenreNm": "\uae30\ud0c0", "directors": [], "companys": []}, {"movieCd": "20202490", "movieNm": "\uc544\uba54\ub9ac\uce78 \uc560\ub2c8\uba40\uc2a4", "movieNmEn": "American Animals", "prdtYear": "2018", "openDt": "", "typeNm": "\uc7a5\ud3b8", "prdtStatNm": "\uae30\ud0c0", "nationAlt": "\ubbf8\uad6d,\uc601\uad6d", "genreAlt": "\ubc94\uc8c4,\ub4dc\ub77c\ub9c8", "repNationNm": "\ubbf8\uad6d", "repGenreNm": "\ubc94\uc8c4", "directors": [], "companys": []}, {"movieCd": "20202489", "movieNm": "\uc800\uc2a4\ud2b8 \uac9f\ud305 \uc2a4\ud0c0\ud2f0\ub4dc", "movieNmEn": "Just Getting Started", "prdtYear": "2017", "openDt": "", "typeNm": "\uc7a5\ud3b8", "prdtStatNm": "\uae30\ud0c0", "nationAlt": "\ubbf8\uad6d", "genreAlt": "\ucf54\ubbf8\ub514,\ubc94\uc8c4", "repNationNm": "\ubbf8\uad6d", "repGenreNm": "\ucf54\ubbf8\ub514", "directors": [{"peopleNm": "\ub860 \uc258\ud1a4"}], "companys": []}, {"movieCd": "20183722", "movieNm": "\ub370\ub4dc \uc5b4\uac8c\uc778", "movieNmEn": "Dead Again", "prdtYear": "2017", "openDt": "", "typeNm": "\uc7a5\ud3b8", "prdtStatNm": "\uae30\ud0c0", "nationAlt": "\ubbf8\uad6d,\ud55c\uad6d", "genreAlt": "\uc2a4\ub9b4\ub7ec,\uacf5\ud3ec(\ud638\ub7ec),\uba5c\ub85c/\ub85c\ub9e8\uc2a4", "repNationNm": "\ubbf8\uad6d", "repGenreNm": "\uc2a4\ub9b4\ub7ec", "directors": [{"peopleNm": "\ub370\uc774\ube0c \uc2e4\ubc84\ub9e8"}], "companys": []}, {"movieCd": "20183144", "movieNm": "\uc120\uc885 \ubb34\ubb38\uad00", "movieNmEn": "", "prdtYear": "2016", "openDt": "20181213", "typeNm": "\uc7a5\ud3b8", "prdtStatNm": "\uac1c\ubd09", "nationAlt": "\ud55c\uad6d", "genreAlt": "\ub4dc\ub77c\ub9c8", "repNationNm": "\ud55c\uad6d", "repGenreNm": "\ub4dc\ub77c\ub9c8", "directors": [{"peopleNm": "\uc724\uc6a9\uc9c4"}], "companys": []}, {"movieCd": "20202429", "movieNm": "\uc548\uc2dd", "movieNmEn": "", "prdtYear": "2019", "openDt": "", "typeNm": "\ub2e8\ud3b8", "prdtStatNm": "\uae30\ud0c0", "nationAlt": "\ud55c\uad6d", "genreAlt": "\uae30\ud0c0", "repNationNm": "\ud55c\uad6d", "repGenreNm": "\uae30\ud0c0", "directors": [{"peopleNm": "\uc774\uc0c1\ud6c8"}], "companys": []}, {"movieCd": "20202428", "movieNm": "\ubc1c\uce58", "movieNmEn": "", "prdtYear": "2020", "openDt": "", "typeNm": "\ub2e8\ud3b8", "prdtStatNm": "\uae30\ud0c0", "nationAlt": "\ud55c\uad6d", "genreAlt": "\uae30\ud0c0", "repNationNm": "\ud55c\uad6d", "repGenreNm": "\uae30\ud0c0", "directors": [], "companys": []}, {"movieCd": "20202486", "movieNm": "\ub864\ub9c1 \ud22c \uc720", "movieNmEn": "Rolling to You", "prdtYear": "2018", "openDt": "", "typeNm": "\uc7a5\ud3b8", "prdtStatNm": "\uae30\ud0c0", "nationAlt": "\ud504\ub791\uc2a4", "genreAlt": "\ucf54\ubbf8\ub514,\uba5c\ub85c/\ub85c\ub9e8\uc2a4", "repNationNm": "\ud504\ub791\uc2a4", "repGenreNm": "\ucf54\ubbf8\ub514", "directors": [{"peopleNm": "\ud504\ub791\ud06c \ub450\ubcf4\uc2a5"}], "companys": []}, {"movieCd": "20030060", "movieNm": "\ud380\uce58 \ub4dc\ub801\ud06c \ub7ec\ube0c", "movieNmEn": "Punch Drunk Love", "prdtYear": "2002", "openDt": "20030508", "typeNm": "\uc7a5\ud3b8", "prdtStatNm": "\uac1c\ubd09", "nationAlt": "\ubbf8\uad6d", "genreAlt": "\uba5c\ub85c/\ub85c\ub9e8\uc2a4,\ucf54\ubbf8\ub514", "repNationNm": "\ubbf8\uad6d", "repGenreNm": "\uba5c\ub85c/\ub85c\ub9e8\uc2a4", "directors": [{"peopleNm": "\ud3f4 \ud1a0\ub9c8\uc2a4 \uc564\ub354\uc2a8"}], "companys": [{"companyCd": "20061735", "companyNm": "\ucf5c\ub7fc\ube44\uc544\ud2b8\ub77c\uc774\uc2a4\ud0c0"}]}, {"movieCd": "20202427", "movieNm": "\ub354 \ub370\uc774", "movieNmEn": "", "prdtYear": "2020", "openDt": "", "typeNm": "\ub2e8\ud3b8", "prdtStatNm": "\uae30\ud0c0", "nationAlt": "\ud55c\uad6d", "genreAlt": "\uae30\ud0c0", "repNationNm": "\ud55c\uad6d", "repGenreNm": "\uae30\ud0c0", "directors": [], "companys": []}, {"movieCd": "20202035", "movieNm": "\uc2a4\ub098\uc774\ud37c: \ub77c\uc2a4\ud2b8 \ubbf8\uc158", "movieNmEn": "Submission", "prdtYear": "2019", "openDt": "", "typeNm": "\uc7a5\ud3b8", "prdtStatNm": "\uae30\ud0c0", "nationAlt": "\ubbf8\uad6d", "genreAlt": "\uc804\uc7c1,\uc561\uc158", "repNationNm": "\ubbf8\uad6d", "repGenreNm": "\uc804\uc7c1", "directors": [], "companys": []}, {"movieCd": "20050042", "movieNm": "\uc9c0\uae08, \ub9cc\ub098\ub7ec \uac11\ub2c8\ub2e4", "movieNmEn": "Be With You", "prdtYear": "2004", "openDt": "20050325", "typeNm": "\uc7a5\ud3b8", "prdtStatNm": "\uac1c\ubd09", "nationAlt": "\uc77c\ubcf8", "genreAlt": "\ub4dc\ub77c\ub9c8,\uba5c\ub85c/\ub85c\ub9e8\uc2a4,\ud310\ud0c0\uc9c0", "repNationNm": "\uc77c\ubcf8", "repGenreNm": "\ub4dc\ub77c\ub9c8", "directors": [{"peopleNm": "\ub3c4\uc774 \ub178\ubd80\ud788\ub85c"}], "companys": [{"companyCd": "20101515", "companyNm": "\ub3c4\ud638\ucfe0\uc2e0\uc0e4"}]}, {"movieCd": "20202405", "movieNm": "\ubbf8\ubbf8(\u7f8e\u5473): \uad81\uadf9\uc758 \uc2dd\uc0ac", "movieNmEn": "Aesthetic Taste", "prdtYear": "2020", "openDt": "", "typeNm": "\ub2e8\ud3b8", "prdtStatNm": "\uae30\ud0c0", "nationAlt": "\ud55c\uad6d", "genreAlt": "\uacf5\ud3ec(\ud638\ub7ec),\ucf54\ubbf8\ub514", "repNationNm": "\ud55c\uad6d", "repGenreNm": "\uacf5\ud3ec(\ud638\ub7ec)", "directors": [{"peopleNm": "\ud55c\uc7ac\uc6d0"}], "companys": []}, {"movieCd": "20040703", "movieNm": "\uc870\uc81c, \ud638\ub791\uc774 \uadf8\ub9ac\uace0 \ubb3c\uace0\uae30\ub4e4", "movieNmEn": "Josee, The Tiger And The Fish", "prdtYear": "2003", "openDt": "20041029", "typeNm": "\uc7a5\ud3b8", "prdtStatNm": "\uac1c\ubd09", "nationAlt": "\uc77c\ubcf8", "genreAlt": "\ub4dc\ub77c\ub9c8", "repNationNm": "\uc77c\ubcf8", "repGenreNm": "\ub4dc\ub77c\ub9c8", "directors": [{"peopleNm": "\uc774\ub204\ub3c4 \uc787\uc2e0 "}], "companys": [{"companyCd": "20101897", "companyNm": "\uc544\uc2a4\ubbf9\uc5d0\uc774\uc2a4\uc5d4\ud130\ud14c\uc778\uba3c\ud2b8"}]}, {"movieCd": "20194191", "movieNm": "\ubcf8 \ud22c \ub4dc\ub77c\uc774\ube0c ", "movieNmEn": "Born2Drive", "prdtYear": "2019", "openDt": "20191212", "typeNm": "\uc7a5\ud3b8", "prdtStatNm": "\uac1c\ubd09", "nationAlt": "\ub178\ub974\uc6e8\uc774", "genreAlt": "\ub2e4\ud050\uba58\ud130\ub9ac", "repNationNm": "\ub178\ub974\uc6e8\uc774", "repGenreNm": "\ub2e4\ud050\uba58\ud130\ub9ac", "directors": [{"peopleNm": "\ub2e4\ub2c8\uc5d8 \ud30c\ub808"}], "companys": []}, {"movieCd": "20201697", "movieNm": "\uc131\ub09c \ub124\uace0", "movieNmEn": "Raging Nego", "prdtYear": "2020", "openDt": "", "typeNm": "\ub2e8\ud3b8", "prdtStatNm": "\uae30\ud0c0", "nationAlt": "\ud55c\uad6d", "genreAlt": "\ucf54\ubbf8\ub514,\uc561\uc158", "repNationNm": "\ud55c\uad6d", "repGenreNm": "\ucf54\ubbf8\ub514", "directors": [{"peopleNm": "\ud55c\uc7ac\uc6d0"}], "companys": []}, {"movieCd": "20201923", "movieNm": "\ubaa8\ud638\ud55c \uc695\ub9dd\uc758 \ub300\uc0c1", "movieNmEn": "that obscure object of desire", "prdtYear": "2020", "openDt": "", "typeNm": "\uc7a5\ud3b8", "prdtStatNm": "\uae30\ud0c0", "nationAlt": "\ud55c\uad6d", "genreAlt": "\uae30\ud0c0", "repNationNm": "\ud55c\uad6d", "repGenreNm": "\uae30\ud0c0", "directors": [{"peopleNm": "\uae40\uc751\uc218"}], "companys": []}, {"movieCd": "20201600", "movieNm": "\ubb3c\uc758", "movieNmEn": "Things Meaning", "prdtYear": "2019", "openDt": "", "typeNm": "\ub2e8\ud3b8", "prdtStatNm": "\uae30\ud0c0", "nationAlt": "\ud55c\uad6d", "genreAlt": "\ub4dc\ub77c\ub9c8", "repNationNm": "\ud55c\uad6d", "repGenreNm": "\ub4dc\ub77c\ub9c8", "directors": [{"peopleNm": "\uc815\uc9c4\ud601"}], "companys": []}, {"movieCd": "20201599", "movieNm": "\uac00\ud654\ub9cc\uc0ac\uc131", "movieNmEn": "Family Symphony", "prdtYear": "2020", "openDt": "", "typeNm": "\ub2e8\ud3b8", "prdtStatNm": "\uae30\ud0c0", "nationAlt": "\ud55c\uad6d", "genreAlt": "\ub4dc\ub77c\ub9c8", "repNationNm": "\ud55c\uad6d", "repGenreNm": "\ub4dc\ub77c\ub9c8", "directors": [], "companys": []}, {"movieCd": "20201598", "movieNm": "\ud76c", "movieNmEn": "Be Aflame", "prdtYear": "2019", "openDt": "", "typeNm": "\ub2e8\ud3b8", "prdtStatNm": "\uae30\ud0c0", "nationAlt": "\ud55c\uad6d", "genreAlt": "\ub4dc\ub77c\ub9c8", "repNationNm": "\ud55c\uad6d", "repGenreNm": "\ub4dc\ub77c\ub9c8", "directors": [{"peopleNm": "\ud64d\ud574\uc6d0"}], "companys": []}, {"movieCd": "20201611", "movieNm": "\uacc4\uc808\uc758 \ub05d", "movieNmEn": "Summer date", "prdtYear": "2020", "openDt": "", "typeNm": "\ub2e8\ud3b8", "prdtStatNm": "\uae30\ud0c0", "nationAlt": "\ud55c\uad6d", "genreAlt": "\ub4dc\ub77c\ub9c8", "repNationNm": "\ud55c\uad6d", "repGenreNm": "\ub4dc\ub77c\ub9c8", "directors": [], "companys": []}, {"movieCd": "20201610", "movieNm": "\uadf8\uacf3\uc5d0 \uac00\uba74", "movieNmEn": "If you go there", "prdtYear": "2020", "openDt": "", "typeNm": "\ub2e8\ud3b8", "prdtStatNm": "\uae30\ud0c0", "nationAlt": "\ud55c\uad6d", "genreAlt": "\ub2e4\ud050\uba58\ud130\ub9ac", "repNationNm": "\ud55c\uad6d", "repGenreNm": "\ub2e4\ud050\uba58\ud130\ub9ac", "directors": [], "companys": []}, {"movieCd": "20201633", "movieNm": "\ub0af\uc775\uc740 \uc5ec\ub984", "movieNmEn": "VISITOR", "prdtYear": "2007", "openDt": "", "typeNm": "\ub2e8\ud3b8", "prdtStatNm": "\uae30\ud0c0", "nationAlt": "\ud55c\uad6d", "genreAlt": "\ub4dc\ub77c\ub9c8", "repNationNm": "\ud55c\uad6d", "repGenreNm": "\ub4dc\ub77c\ub9c8", "directors": [{"peopleNm": "\ubc15\uc131\ub9bc"}], "companys": []}, {"movieCd": "20201612", "movieNm": "\ube48 \uacf3\uc5d0\uc11c", "movieNmEn": "Empty Days", "prdtYear": "1997", "openDt": "", "typeNm": "\ub2e8\ud3b8", "prdtStatNm": "\uae30\ud0c0", "nationAlt": "\ud55c\uad6d", "genreAlt": "\ub4dc\ub77c\ub9c8", "repNationNm": "\ud55c\uad6d", "repGenreNm": "\ub4dc\ub77c\ub9c8", "directors": [], "companys": []}, {"movieCd": "20202476", "movieNm": "\ud53c\uc544\ub2c8\uc2a4\ud2b8\uc758 \ub9c8\uc9c0\ub9c9 \uc778\ud130\ubdf0", "movieNmEn": "CODA", "prdtYear": "2019", "openDt": "20201119", "typeNm": "\uc7a5\ud3b8", "prdtStatNm": "\uac1c\ubd09", "nationAlt": "\uce90\ub098\ub2e4", "genreAlt": "\ub4dc\ub77c\ub9c8,\ubba4\uc9c0\uceec", "repNationNm": "\uce90\ub098\ub2e4", "repGenreNm": "\ub4dc\ub77c\ub9c8", "directors": [{"peopleNm": "\ud074\ub85c\ub4dc \ub77c\ub871\ub4dc"}], "companys": []}, {"movieCd": "20200050", "movieNm": "\uacf5\uc874", "movieNmEn": "Coexistence", "prdtYear": "2018", "openDt": "", "typeNm": "\ub2e8\ud3b8", "prdtStatNm": "\uae30\ud0c0", "nationAlt": "\ud55c\uad6d", "genreAlt": "\ub4dc\ub77c\ub9c8", "repNationNm": "\ud55c\uad6d", "repGenreNm": "\ub4dc\ub77c\ub9c8", "directors": [{"peopleNm": "\uc9c0\uc6c5\ubc30"}], "companys": [{"companyCd": "2019981", "companyNm": "\uc8fc\uc2dd\ud68c\uc0ac \ud544\uc528\ub124"}]}, {"movieCd": "20201985", "movieNm": "\uc5e0\ud2f0\ub9e8", "movieNmEn": "The Empty Man", "prdtYear": "2019", "openDt": "20201119", "typeNm": "\uc7a5\ud3b8", "prdtStatNm": "\uac1c\ubd09", "nationAlt": "\ubbf8\uad6d", "genreAlt": "\uacf5\ud3ec(\ud638\ub7ec),\ubbf8\uc2a4\ud130\ub9ac", "repNationNm": "\ubbf8\uad6d", "repGenreNm": "\uacf5\ud3ec(\ud638\ub7ec)", "directors": [], "companys": []}, {"movieCd": "20201178", "movieNm": "\uc5d1\uc124\ub7f0\ud2b8 \uc5b4\ub4dc\ubca4\uccd0 3", "movieNmEn": "Bill & Ted Face the Music", "prdtYear": "2020", "openDt": "20201119", "typeNm": "\uc7a5\ud3b8", "prdtStatNm": "\uac1c\ubd09", "nationAlt": "\ubbf8\uad6d", "genreAlt": "\uc5b4\ub4dc\ubca4\ucc98,\ucf54\ubbf8\ub514", "repNationNm": "\ubbf8\uad6d", "repGenreNm": "\uc5b4\ub4dc\ubca4\ucc98", "directors": [{"peopleNm": "\ub518 \ud328\ub9ac\uc18c\ud2b8"}], "companys": []}, {"movieCd": "20202310", "movieNm": "\ub098\ub294 \uc57c\ud55c \uc5ec\uc790\uac00 \uc88b\ub2e4 4 - \ubb34\uc0ad\uc81c\ud310", "movieNmEn": "", "prdtYear": "2020", "openDt": "20201118", "typeNm": "\uc7a5\ud3b8", "prdtStatNm": "\uac1c\ubd09", "nationAlt": "\ud55c\uad6d", "genreAlt": "\uba5c\ub85c/\ub85c\ub9e8\uc2a4", "repNationNm": "\ud55c\uad6d", "repGenreNm": "\uba5c\ub85c/\ub85c\ub9e8\uc2a4", "directors": [{"peopleNm": "\uae40\uc885\uc11d"}], "companys": [{"companyCd": "20176201", "companyNm": "\ubaa8\ud788\ub610\ud544\ub984"}]}, {"movieCd": "20202407", "movieNm": "\ub3c5\ubc15", "movieNmEn": "", "prdtYear": "2019", "openDt": "", "typeNm": "\ub2e8\ud3b8", "prdtStatNm": "\uae30\ud0c0", "nationAlt": "\ud55c\uad6d", "genreAlt": "\uae30\ud0c0", "repNationNm": "\ud55c\uad6d", "repGenreNm": "\uae30\ud0c0", "directors": [{"peopleNm": "\uc774\uac00\uc601"}], "companys": []}, {"movieCd": "20202395", "movieNm": "\ubbf8\ub140\ub4e4\uc758 \uc0c9\uc218\ub2e4", "movieNmEn": "", "prdtYear": "2020", "openDt": "", "typeNm": "\uc7a5\ud3b8", "prdtStatNm": "\uae30\ud0c0", "nationAlt": "\uc77c\ubcf8", "genreAlt": "\ub4dc\ub77c\ub9c8", "repNationNm": "\uc77c\ubcf8", "repGenreNm": "\ub4dc\ub77c\ub9c8", "directors": [], "companys": []}, {"movieCd": "20202396", "movieNm": "\ubcc0\ud0dc\ud559\uc6d0\uc758 \ubbf8\ub140 \uc218\uac15\uc0dd", "movieNmEn": "", "prdtYear": "2020", "openDt": "", "typeNm": "\uc7a5\ud3b8", "prdtStatNm": "\uae30\ud0c0", "nationAlt": "\uc77c\ubcf8", "genreAlt": "\ub4dc\ub77c\ub9c8", "repNationNm": "\uc77c\ubcf8", "repGenreNm": "\ub4dc\ub77c\ub9c8", "directors": [], "companys": []}, {"movieCd": "20202406", "movieNm": "\ub354 \ud0a4\ub4dc ", "movieNmEn": "The Kid", "prdtYear": "2019", "openDt": "", "typeNm": "\uc7a5\ud3b8", "prdtStatNm": "\uae30\ud0c0", "nationAlt": "\ubbf8\uad6d", "genreAlt": "\uae30\ud0c0", "repNationNm": "\ubbf8\uad6d", "repGenreNm": "\uae30\ud0c0", "directors": [], "companys": []}, {"movieCd": "20200418", "movieNm": "\uace0\uc694\ud55c \uc544\uce68", "movieNmEn": "", "prdtYear": "2020", "openDt": "", "typeNm": "\uc7a5\ud3b8", "prdtStatNm": "\ucd2c\uc601\uc9c4\ud589", "nationAlt": "", "genreAlt": "\uae30\ud0c0", "repNationNm": "", "repGenreNm": "\uae30\ud0c0", "directors": [{"peopleNm": "\ub4dc\ub2c8 \ub370\ub974\ucfe0\ub974"}], "companys": []}, {"movieCd": "20205258", "movieNm": "\uad6c\uc9c1\uc790\ub4e4", "movieNmEn": "The Interviewees", "prdtYear": "2020", "openDt": "20201112", "typeNm": "\uc7a5\ud3b8", "prdtStatNm": "\uac1c\ubd09", "nationAlt": "\ud55c\uad6d", "genreAlt": "SF,\ub4dc\ub77c\ub9c8", "repNationNm": "\ud55c\uad6d", "repGenreNm": "SF", "directors": [{"peopleNm": "\ud669\uc2b9\uc7ac"}], "companys": [{"companyCd": "20203041", "companyNm": "\uc8fc\uc2dd\ud68c\uc0ac\uc778\uc2dc\uc98c"}]}]}}